LICENSE
MANIFEST.in
README.rst
setup.py
database_email_backend/__init__.py
database_email_backend/admin.py
database_email_backend/backend.py
database_email_backend/fields.py
database_email_backend/models.py
database_email_backend/migrations/0001_initial.py
database_email_backend/migrations/0002_auto__add_attachment.py
database_email_backend/migrations/__init__.py
database_email_backend/templates/admin/database_email_backend/sendemail/change_form.html
database_email_backend/tests/__init__.py
django_database_email_backend.egg-info/PKG-INFO
django_database_email_backend.egg-info/SOURCES.txt
django_database_email_backend.egg-info/dependency_links.txt
django_database_email_backend.egg-info/not-zip-safe
django_database_email_backend.egg-info/top_level.txt