Metadata-Version: 1.0
Name: django-database-email-backend
Version: 0.2.1
Summary: A django EmailBackend for debugging that saves Emails in the database instead of delivering them.
Home-page: http://github.com/stefanfoulis/django-database-email-backend
Author: Stefan Foulis
Author-email: stefan.foulis@gmail.com
License: BSD
Platform: OS Independent
Classifier: Development Status :: 4 - Beta
Classifier: Framework :: Django
Classifier: Intended Audience :: Developers
Classifier: License :: OSI Approved :: BSD License
Classifier: Operating System :: OS Independent
Classifier: Programming Language :: Python
Classifier: Topic :: Internet :: WWW/HTTP
